netsparker_api/Netsparker_Account.py
netsparker_api/Netsparker_Agents.py
netsparker_api/Netsparker_AuditLogs.py
netsparker_api/Netsparker_Issues.py
netsparker_api/Netsparker_Notifications.py
netsparker_api/Netsparker_ScanPolicies.py
netsparker_api/Netsparker_ScanProfiles.py
netsparker_api/Netsparker_Scans.py
netsparker_api/Netsparker_TeamMembers.py
netsparker_api/Netsparker_Technologies.py
netsparker_api/Netsparker_Vulnerability.py
netsparker_api/Netsparker_WebsiteGroups.py
netsparker_api/Netsparker_Websites.py
netsparker_api/__init__.py
netsparker_api-0.2.dist-info/LICENSE
netsparker_api-0.2.dist-info/METADATA
netsparker_api-0.2.dist-info/WHEEL
netsparker_api-0.2.dist-info/top_level.txt
netsparker_api-0.2.dist-info/RECORD
