Metadata-Version: 2.1
Name: netsparker-api
Version: 0.2
Summary: An interface to Netsparker REST API
Home-page: https://github.com/ShinoNoNuma/Netsparker-Rest-API
Author: Samy Younsi (Shino Corp')
Author-email: samyyounsi@hotmail.fr
License: MIT
Keywords: netsparker netsparker_api netsparker_rest netsparker_enterprise netsparker_team
Platform: UNKNOWN
Classifier: Programming Language :: Python :: 3
Classifier: License :: OSI Approved :: MIT License
Requires-Dist: requests (>=1.4)
